ocr/__init__.py
ocr/ocr.py
ocr_meter-0.0.7.dist-info/LICENSE
ocr_meter-0.0.7.dist-info/METADATA
ocr_meter-0.0.7.dist-info/WHEEL
ocr_meter-0.0.7.dist-info/top_level.txt
ocr_meter-0.0.7.dist-info/RECORD
