Metadata-Version: 2.1
Name: ocr-meter
Version: 0.0.7
Summary: A small example package
Home-page: https://github.com/pypa/sampleproject
Author: Cuong Cao
Author-email: cuong091200@gmail.com
Project-URL: Bug Tracker, https://github.com/pypa/sampleproject/issues
Classifier: Programming Language :: Python :: 3
Classifier: License :: OSI Approved :: MIT License
Classifier: Operating System :: OS Independent
Requires-Python: >=3.8
License-File: LICENSE
Requires-Dist: numpy (==1.23.4)
Requires-Dist: opencv-python (==4.5.5.64)
Requires-Dist: paddleocr (==2.6.0.2)
Requires-Dist: paddlepaddle
Requires-Dist: easyocr (==1.6.2)
